baribal/__init__.py
baribal/core.py
baribal/utils.py
baribal/viz.py
baribal-0.2.1.dist-info/LICENSE
baribal-0.2.1.dist-info/METADATA
baribal-0.2.1.dist-info/WHEEL
baribal-0.2.1.dist-info/top_level.txt
baribal-0.2.1.dist-info/RECORD
